corradin_ovp_utils/__init__.py
corradin_ovp_utils/_nbdev.py
corradin_ovp_utils/catalog.py
corradin_ovp_utils/core.py
corradin_ovp_utils/datasets/CombinedGenoPheno.py
corradin_ovp_utils/datasets/OVPDataset.py
corradin_ovp_utils/datasets/__init__.py
corradin_ovp_utils/datasets/genetic_file/Bgen.py
corradin_ovp_utils/datasets/genetic_file/Gen.py
corradin_ovp_utils/datasets/genetic_file/__init__.py
corradin_ovp_utils/datasets/sample_file.py
corradin_ovp_utils/datasets/schemas.py
corradin_ovp_utils/datasets/utils.py
corradin_ovp_utils/odds_ratio.py
corradin_ovp_utils-0.2.0.dist-info/LICENSE
corradin_ovp_utils-0.2.0.dist-info/WHEEL
corradin_ovp_utils-0.2.0.dist-info/METADATA
corradin_ovp_utils-0.2.0.dist-info/RECORD
