Metadata-Version: 2.1
Name: corradin-ovp-utils
Version: 0.2.0
Summary: 
Author: An
Author-email: hoangthienan95@gmail.com
Requires-Python: >=3.8,<3.9
Classifier: Programming Language :: Python :: 3
Classifier: Programming Language :: Python :: 3.8
Requires-Dist: bgen-reader (>=4.0.7,<5.0.0)
Requires-Dist: ipython (==7.10)
Requires-Dist: jedi (<0.18.0)
Requires-Dist: portray (>=1.5.2,<2.0.0)
